plumber_agent/__init__.py
plumber_agent/agent_server.py
plumber_agent/blender_server_manager_filebased.py
plumber_agent/cli.py
plumber_agent/connection_manager.py
plumber_agent/cross_platform_utils.py
plumber_agent/dcc_discovery.py
plumber_agent/dcc_executor.py
plumber_agent/dcc_executor_v2.py
plumber_agent/houdini_server_manager_filebased.py
plumber_agent/main.py
plumber_agent/maya_server_manager.py
plumber_agent/maya_server_manager_filebased.py
plumber_agent/service_manager.py
plumber_agent/__pycache__/__init__.cpython-310.pyc
plumber_agent/__pycache__/agent_server.cpython-310.pyc
plumber_agent/__pycache__/blender_server_manager_filebased.cpython-310.pyc
plumber_agent/__pycache__/cli.cpython-310.pyc
plumber_agent/__pycache__/connection_manager.cpython-310.pyc
plumber_agent/__pycache__/cross_platform_utils.cpython-310.pyc
plumber_agent/__pycache__/dcc_discovery.cpython-310.pyc
plumber_agent/__pycache__/dcc_executor.cpython-310.pyc
plumber_agent/__pycache__/houdini_server_manager_filebased.cpython-310.pyc
plumber_agent/__pycache__/maya_server_manager_filebased.cpython-310.pyc
plumber_agent/__pycache__/service_manager.cpython-310.pyc
plumber_agent/dcc_plugins/__init__.py
plumber_agent/dcc_plugins/base_plugin.py
plumber_agent/dcc_plugins/blender_plugin.py
plumber_agent/dcc_plugins/houdini_plugin.py
plumber_agent/dcc_plugins/maya_plugin.py
plumber_agent/dcc_plugins/plugin_manager.py
plumber_agent/dcc_plugins/__pycache__/__init__.cpython-310.pyc
plumber_agent/dcc_plugins/__pycache__/base_plugin.cpython-310.pyc
plumber_agent/dcc_plugins/__pycache__/plugin_manager.cpython-310.pyc
plumber_agent/services/__init__.py
plumber_agent/services/launchd_handler.py
plumber_agent/services/systemd_handler.py
plumber_agent/services/windows_handler.py
plumber_agent/services/__pycache__/__init__.cpython-310.pyc
plumber_agent/services/__pycache__/launchd_handler.cpython-310.pyc
plumber_agent/services/__pycache__/systemd_handler.cpython-310.pyc
plumber_agent-1.0.2.dist-info/METADATA
plumber_agent-1.0.2.dist-info/WHEEL
plumber_agent-1.0.2.dist-info/entry_points.txt
plumber_agent-1.0.2.dist-info/top_level.txt
plumber_agent-1.0.2.dist-info/RECORD
